sidas/__init__.py
sidas/py.typed
sidas/cli/__init__.py
sidas/cli/cli.py
sidas/core/__init__.py
sidas/core/asset.py
sidas/core/asset_id.py
sidas/core/config.py
sidas/core/coordinator.py
sidas/core/data_persister.py
sidas/core/exceptions.py
sidas/core/loader.py
sidas/core/meta.py
sidas/core/meta_persister.py
sidas/extensions/__init__.py
sidas/extensions/assets/__init__.py
sidas/extensions/assets/downstream_asset.py
sidas/extensions/assets/scheduled_asset.py
sidas/extensions/assets/simple_asset.py
sidas/extensions/coordinators/__init__.py
sidas/extensions/coordinators/simple.py
sidas/extensions/data_persisters/__init__.py
sidas/extensions/data_persisters/dataclass_persister.py
sidas/extensions/data_persisters/duckdb_persister.py
sidas/extensions/data_persisters/json_persister.py
sidas/extensions/data_persisters/memory_persister.py
sidas/extensions/data_persisters/pandas_persister.py
sidas/extensions/data_persisters/polars_persister.py
sidas/extensions/encoders/__init__.py
sidas/extensions/encoders/json.py
sidas/extensions/meta_persisters/__init__.py
sidas/extensions/meta_persisters/dynamodb.py
sidas/extensions/meta_persisters/file.py
sidas/extensions/meta_persisters/simple.py
sidas/extensions/meta_persisters/database/__init__.py
sidas/extensions/meta_persisters/database/entities.py
sidas/extensions/meta_persisters/database/implementation.py
sidas/extensions/resources/__init__.py
sidas/extensions/resources/aws.py
sidas/extensions/resources/databases.py
sidas/extensions/resources/folder.py
sidas-0.2.13.dist-info/METADATA
sidas-0.2.13.dist-info/WHEEL
sidas-0.2.13.dist-info/entry_points.txt
sidas-0.2.13.dist-info/RECORD
