Metadata-Version: 2.4
Name: sidas
Version: 0.2.13
Author-email: Christian Kranemann <christian.kranemann@al-ko.com>
License: MIT
Requires-Python: >=3.12
Requires-Dist: boto3>=1.36.11
Requires-Dist: click>=8.1.8
Requires-Dist: croniter>=1.4.1
Requires-Dist: dacite>=1.9.2
Requires-Dist: dataclasses-json>=0.6.7
Requires-Dist: duckdb>=1.2.1
Requires-Dist: pandas>=2.2.3
Requires-Dist: polars>=1.24.0
Requires-Dist: pyarrow>=19.0.1
Requires-Dist: pydantic>=2.10.6
Requires-Dist: smart-open[s3]>=7.1.0
Requires-Dist: sqlalchemy>=2.0.38
Provides-Extra: test
Requires-Dist: pytest-cov>=4.1.0; extra == 'test'
Requires-Dist: pytest>=7.4.2; extra == 'test'
